datatailr/__init__.py
datatailr/acl.py
datatailr/blob.py
datatailr/dt_json.py
datatailr/errors.py
datatailr/group.py
datatailr/logging.py
datatailr/tag.py
datatailr/user.py
datatailr/utils.py
datatailr/version.py
datatailr/wrapper.py
datatailr/build/__init__.py
datatailr/build/image.py
datatailr/excel/__init__.py
datatailr/excel/addin.py
datatailr/excel/stubs.py
datatailr/sbin/datatailr_cli.py
datatailr/sbin/datatailr_run.py
datatailr/sbin/datatailr_run_app.py
datatailr/sbin/datatailr_run_batch.py
datatailr/sbin/datatailr_run_excel.py
datatailr/sbin/datatailr_run_service.py
datatailr/scheduler/__init__.py
datatailr/scheduler/arguments_cache.py
datatailr/scheduler/base.py
datatailr/scheduler/batch.py
datatailr/scheduler/batch_decorator.py
datatailr/scheduler/constants.py
datatailr/scheduler/job.py
datatailr/scheduler/schedule.py
datatailr/scheduler/utils.py
datatailr/scheduler/workflow.py
datatailr-0.1.99.data/data/datatailr_demo/README.md
datatailr-0.1.99.dist-info/licenses/LICENSE
datatailr_demo/README.md
datatailr_demo/__init__.py
datatailr_demo/examples.py
datatailr_demo/dashboards/__init__.py
datatailr_demo/dashboards/app.py
datatailr_demo/data_pipelines/__init__.py
datatailr_demo/data_pipelines/data_processing.py
datatailr_demo/excel_addins/__init__.py
datatailr_demo/excel_addins/addin.py
datatailr_demo/services/__init__.py
datatailr_demo/services/flask_service.py
remote_cli/__init__.py
remote_cli/remote_cli.py
datatailr-0.1.99.dist-info/METADATA
datatailr-0.1.99.dist-info/WHEEL
datatailr-0.1.99.dist-info/entry_points.txt
datatailr-0.1.99.dist-info/top_level.txt
datatailr-0.1.99.dist-info/RECORD
