Metadata-Version: 2.4
Name: datatailr
Version: 0.1.99
Summary: Ready-to-Use Platform That Drives Business Insights
Author-email: Datatailr <info@datatailr.com>
License-Expression: MIT
Project-URL: homepage, https://www.datatailr.com/
Project-URL: documentation, https://docs.datatailr.com/
Classifier: Programming Language :: Python :: 3
Classifier: Programming Language :: Python :: 3 :: Only
Classifier: Programming Language :: Python :: 3.9
Classifier: Programming Language :: Python :: 3.10
Classifier: Programming Language :: Python :: 3.11
Classifier: Programming Language :: Python :: 3.12
Classifier: Programming Language :: Python :: 3.13
Classifier: Environment :: Console
Classifier: Operating System :: OS Independent
Classifier: Topic :: Scientific/Engineering
Requires-Python: >=3.9
License-File: LICENSE
Provides-Extra: dev
Requires-Dist: ruff; extra == "dev"
Requires-Dist: pre-commit; extra == "dev"
Requires-Dist: mypy; extra == "dev"
Requires-Dist: types-setuptools; extra == "dev"
Requires-Dist: toml; extra == "dev"
Requires-Dist: coverage; extra == "dev"
Requires-Dist: sphinx-rtd-theme; extra == "dev"
Requires-Dist: sphinx; extra == "dev"
Requires-Dist: sphinx-autodoc-typehints; extra == "dev"
Requires-Dist: sphinx-autosummary; extra == "dev"
Requires-Dist: sphinx-design; extra == "dev"
Requires-Dist: sphinx-copybutton; extra == "dev"
Requires-Dist: myst-parser; extra == "dev"
Dynamic: license-file
